ipywalrus.py
ipywalrus-0.2.dist-info/LICENSE
ipywalrus-0.2.dist-info/METADATA
ipywalrus-0.2.dist-info/WHEEL
ipywalrus-0.2.dist-info/top_level.txt
ipywalrus-0.2.dist-info/RECORD
