Metadata-Version: 2.1
Name: ipywalrus
Version: 0.2
Summary: ('IPython extension which allows assignment expressions (:=)', 'at the top level of an expression statement')
Home-page: http://github.com/frenzymadness/ipywalrus
Author: Lumír Balhar
Author-email: frenzy.madness@gmail.com
License: MIT
Platform: UNKNOWN
Requires-Python: >=3.8
